polywrap_plugin/__init__.py
polywrap_plugin/module.py
polywrap_plugin/package.py
polywrap_plugin/py.typed
polywrap_plugin/resolution_context_override_client.py
polywrap_plugin/wrapper.py
polywrap_plugin-0.1.2.dist-info/METADATA
polywrap_plugin-0.1.2.dist-info/WHEEL
polywrap_plugin-0.1.2.dist-info/RECORD
