Metadata-Version: 2.1
Name: polywrap-plugin
Version: 0.1.2
Summary: Polywrap Plugin package
Author: Cesar
Author-email: cesar@polywrap.io
Requires-Python: >=3.10,<4.0
Classifier: Programming Language :: Python :: 3
Classifier: Programming Language :: Python :: 3.10
Classifier: Programming Language :: Python :: 3.11
Requires-Dist: polywrap-core (==0.1.2)
Requires-Dist: polywrap-manifest (==0.1.2)
Requires-Dist: polywrap-msgpack (==0.1.2)
